{"pageProps":{"product":{"id":"x0iRTNeBJBRUdOLp015H","name":"Мягкая мебель ГРАНД","price":153000,"imageUrls":["https://label-com.ru/images/virtuemart/product/grand2.jpeg"],"category":"Мягкая мебель","originalUrl":"https://label-com.ru/katalog/myagkaya-mebel/myagkaya-mebel-grand-detail.html","rating":0,"reviews":[],"createdAt":{"_seconds":1764053466,"_nanoseconds":36000000},"description":"Представляем Вашему вниманию коллекцию мягкой мебели ГРАНД от Aura – воплощение изысканности и комфорта, созданное для ценителей безупречного стиля. Этот комплект, состоящий из роскошного дивана и двух элегантных кресел, привносит в интерьер ощущение гармонии и утонченности. Стиль «ГРАНД» можно охарактеризовать как современную классику, где строгие линии встречаются с мягкими изгибами и выразительными деталями, создавая атмосферу уюта и респектабельности.\n\nОбивка комплекта выполнена в глубоком, благородном оттенке, напоминающем темный шоколад или насыщенный антрацит, что придает мебели особый шик. Материал, обладающий легким матовым блеском и приятной на ощупь фактурой, обещает долговечность и легкость в уходе. Особое внимание привлекает мастерская отделка: выразительная контрастная стежка светлого оттенка, которая подчеркивает контуры и создает эффектный акцент. На спинках и сиденьях кресел, а также по бокам дивана, мы видим изысканную ромбовидную прострочку, добавляющую объема и фактурности.\n\nКаждый элемент комплекта ГРАНД продуман для максимального комфорта. Пышные подушки сидений и спинок, а также дополнительные декоративные подушки, приглашают расслабиться после долгого дня. Эргономичные формы и широкие скругленные подлокотники обеспечивают идеальную поддержку. В дизайне органично сочетаются современные тенденции и классические элементы, такие как изящные деревянные ножки и декоративный деревянный молдинг в основании дивана, выполненные в теплом ореховом оттенке. Эти детали не только усиливают эстетическое впечатление, но и гарантируют прочность и надежность конструкции.\n\nМягкая мебель ГРАНД – это не просто функциональный предмет интерьера, это центральный элемент, вокруг которого строится атмосфера вашей гостиной. Она идеально впишется как в просторные апартаменты, так и в уютные студии, создавая зону для комфортного отдыха, дружеских бесед или уединенного времяпровождения. Этот комплект обещает стать истинным украшением Вашего дома, символом вкуса и гостеприимства.\n\n---\n\n**Техническая информация:**\n\n*   **Тип:** Комплект мягкой мебели для гостиной\n*   **Комплектация:** Диван (многоместный), 2 кресла\n*   **Материал:**\n    *   Обивка: Гладкая мебельная ткань / Экокожа (темно-серый/эспрессо оттенок)\n    *   Каркас/Ножки: Массив дерева / Деревянный шпон (теплый коричневый оттенок)\n    *   Декоративная стежка: Нить светлого оттенка\n*   **Цвет:**\n    *   Основной: Темно-серый / Оттенок эспрессо\n    *   Деревянные элементы: Коричневый, оттенок ореха\n    *   Декор: Светлая контрастная строчка\n*   **Особенности:**\n    *   Ромбовидная/стеганая прострочка на спинках и сиденьях кресел, а также на боковинах дивана.\n    *   Декоративные деревянные элементы в основании дивана и в конструкции кресел.\n    *   Контрастная строчка по всем контурам обивки.\n    *   В комплекте декоративные подушки для спины (одного цвета с обивкой).\n    *   Устойчивые конические деревянные ножки.\n    *   Скругленные, широкие подлокотники."}},"__N_SSG":true}